LICENSE
MANIFEST.in
README.rst
setup.cfg
setup.py
config/config-example.yaml
config/obfuscation-example.yaml
configuration/config-example.yml
configuration/obfuscation-example.yml
obfuscation/obfuscation-example.yml
pg_ninja/__init__.py
pg_ninja.egg-info/PKG-INFO
pg_ninja.egg-info/SOURCES.txt
pg_ninja.egg-info/dependency_links.txt
pg_ninja.egg-info/requires.txt
pg_ninja.egg-info/top_level.txt
pg_ninja/lib/__init__.py
pg_ninja/lib/global_lib.py
pg_ninja/lib/mysql_lib.py
pg_ninja/lib/pg_lib.py
pg_ninja/lib/sql_util.py
scripts/pgninja.py
sql/create_schema.sql
sql/drop_schema.sql
sql/upgrade/200_to_201.sql
sql/upgrade/201_to_202.sql
sql/upgrade/202_to_203.sql