Metadata-Version: 1.2
Name: pg-ninja
Version: 2.0.0a1
Summary: MySQL to PostgreSQL replica and migration
Home-page: https://www.transferwise.com/
Author: Transferwise LTD
Author-email: info@transferwise.com
License: Apache 2.0 License
Keywords: postgresql mysql replica migration database
Platform: linux
Classifier: Environment :: Console
Classifier: Intended Audience :: Developers
Classifier: Intended Audience :: Information Technology
Classifier: Intended Audience :: System Administrators
Classifier: Natural Language :: English
Classifier: Operating System :: POSIX :: BSD
Classifier: Operating System :: POSIX :: Linux
Classifier: Programming Language :: Python
Classifier: Programming Language :: Python :: 3
Classifier: Programming Language :: Python :: 3.3
Classifier: Programming Language :: Python :: 3.4
Classifier: Programming Language :: Python :: 3.5
Classifier: Programming Language :: Python :: 3.6
Classifier: Topic :: Database :: Database Engines/Servers
Classifier: Topic :: Other/Nonlisted Topic
Requires-Python: >=3.3
